keraas/__init__.py
keraas/cgan.txt
keraas/diffusion.txt
keraas/face.txt
keraas/image.txt
keraas/mod1.txt
keraas/rcnn.txt
keraas/stable.txt
keraas/vae.txt
keraas/yolo.txt
keraas/yoloc.txt
keraas-1.9.dist-info/METADATA
keraas-1.9.dist-info/WHEEL
keraas-1.9.dist-info/top_level.txt
keraas-1.9.dist-info/RECORD
